apmm-0.1.0.dist-info/METADATA
apmm-0.1.0.dist-info/WHEEL
apmm-0.1.0.dist-info/entry_points.txt
apmm-0.1.0.dist-info/licenses/LICENSE
apmm/__init__.py
apmm/apmcp.py
apmm/apmmcore.cp313-win_amd64.pyd
apmm/py.typed
apmm-0.1.0.dist-info/RECORD
