Metadata-Version: 2.4
Name: apmm
Version: 0.1.0
Requires-Dist: httpx>=0.28.1 ; extra == 'pc'
Requires-Dist: mcp[cli]>=1.9.4 ; extra == 'pc'
Requires-Dist: pygithub>=2.6.1 ; extra == 'pc'
Requires-Dist: toml>=0.10.2 ; extra == 'pc'
Provides-Extra: pc
License-File: LICENSE
Summary: Android Patch Module Manager
Author-email: LIghtJUNction <LIghtJUNction.me@gmail.com>
Requires-Python: >=3.13
